murmurhash-1.0.10.dist-info/RECORD
murmurhash-1.0.10.dist-info/WHEEL
murmurhash-1.0.10.dist-info/METADATA
murmurhash-1.0.10.dist-info/top_level.txt
murmurhash-1.0.10.dist-info/LICENSE
murmurhash/mrmr.cpython-39-x86_64-linux-gnu.so
murmurhash/__init__.py
murmurhash/__init__.pxd
murmurhash/mrmr.pxd
murmurhash/mrmr.pyx
murmurhash/about.py
murmurhash/tests/test_import.py
murmurhash/tests/__init__.py
murmurhash/tests/test_hash.py
murmurhash/include/murmurhash/MurmurHash3.h
murmurhash/include/murmurhash/MurmurHash2.h
